kiv/Keithley_IV.py
kiv/__init__.py
kiv-0.0.6.dist-info/LICENSE.txt
kiv-0.0.6.dist-info/METADATA
kiv-0.0.6.dist-info/WHEEL
kiv-0.0.6.dist-info/top_level.txt
kiv-0.0.6.dist-info/RECORD
